setup.py
opps/__init__.py
opps/fileupload/__init__.py
opps/fileupload/urls.py
opps/fileupload/views.py
opps/fileupload/templatetags/__init__.py
opps/fileupload/templatetags/upload_tags.py
opps_fileupload.egg-info/PKG-INFO
opps_fileupload.egg-info/SOURCES.txt
opps_fileupload.egg-info/dependency_links.txt
opps_fileupload.egg-info/namespace_packages.txt
opps_fileupload.egg-info/top_level.txt